sila2lib_implementations/.gitkeep
sila2lib_implementations/BioREACTOR48/BioREACTOR48Service/BioREACTOR48Service_client.py
sila2lib_implementations/BioREACTOR48/BioREACTOR48Service/BioREACTOR48Service_observable_client.py
sila2lib_implementations/BioREACTOR48/BioREACTOR48Service/BioREACTOR48Service_server.py
sila2lib_implementations/BioREACTOR48/BioREACTOR48Service/BioREACTOR48Service_server_testing.py
sila2lib_implementations/BioREACTOR48/BioREACTOR48Service/DeviceServicer/DeviceServicer_default_arguments.py
sila2lib_implementations/BioREACTOR48/BioREACTOR48Service/DeviceServicer/DeviceServicer_real.py
sila2lib_implementations/BioREACTOR48/BioREACTOR48Service/DeviceServicer/DeviceServicer_servicer.py
sila2lib_implementations/BioREACTOR48/BioREACTOR48Service/DeviceServicer/DeviceServicer_simulation.py
sila2lib_implementations/BioREACTOR48/BioREACTOR48Service/DeviceServicer/__init__.py
sila2lib_implementations/BioREACTOR48/BioREACTOR48Service/DeviceServicer/gRPC/DeviceServicer_pb2.py
sila2lib_implementations/BioREACTOR48/BioREACTOR48Service/DeviceServicer/gRPC/DeviceServicer_pb2_grpc.py
sila2lib_implementations/BioREACTOR48/BioREACTOR48Service/DeviceServicer/gRPC/__init__.py
sila2lib_implementations/BioREACTOR48/BioREACTOR48Service/MotorServicer/MotorServicer_default_arguments.py
sila2lib_implementations/BioREACTOR48/BioREACTOR48Service/MotorServicer/MotorServicer_real.py
sila2lib_implementations/BioREACTOR48/BioREACTOR48Service/MotorServicer/MotorServicer_servicer.py
sila2lib_implementations/BioREACTOR48/BioREACTOR48Service/MotorServicer/MotorServicer_simulation.py
sila2lib_implementations/BioREACTOR48/BioREACTOR48Service/MotorServicer/__init__.py
sila2lib_implementations/BioREACTOR48/BioREACTOR48Service/MotorServicer/gRPC/MotorServicer_pb2.py
sila2lib_implementations/BioREACTOR48/BioREACTOR48Service/MotorServicer/gRPC/MotorServicer_pb2_grpc.py
sila2lib_implementations/BioREACTOR48/BioREACTOR48Service/MotorServicer/gRPC/__init__.py
sila2lib_implementations-0.1.1.dist-info/LICENSE
sila2lib_implementations-0.1.1.dist-info/WHEEL
sila2lib_implementations-0.1.1.dist-info/METADATA
sila2lib_implementations-0.1.1.dist-info/RECORD
