Metadata-Version: 2.1
Name: sila2lib-implementations
Version: 0.1.1
Summary: A package of SiLA drivers for various devices at TUM-BVT
Home-page: https://www.epe.ed.tum.de/en/biovt/home/
License: GPL-3.0-only
Keywords: sila2,laboratory,automation,device integration,hardware
Author: Lukas Bromig
Author-email: lukas.bromig@tum.de
Requires-Python: >=3.7.0,<4.0.0
Classifier: License :: OSI Approved :: GNU General Public License v3 (GPLv3)
Classifier: License :: OSI Approved :: MIT License
Classifier: Operating System :: OS Independent
Classifier: Programming Language :: Python :: 3
Classifier: Programming Language :: Python :: 3.7
Classifier: Programming Language :: Python :: 3.8
Classifier: Programming Language :: Python :: 3.9
Classifier: Programming Language :: Python :: 3.10
Classifier: Programming Language :: Python :: 3
Requires-Dist: pydantic (==1.8.2)
Requires-Dist: pyserial (==3.5)
Requires-Dist: pytest (==6.2.5)
Requires-Dist: python-dotenv (==0.19.1)
Requires-Dist: setuptools (==59.1.0)
Requires-Dist: sila2lib (==0.2.5)
Requires-Dist: wheel (==0.36.0)
Project-URL: Documentation, https://gitlab.com/lukas.bromig/sila2lib_implementations
Project-URL: Repository, https://gitlab.com/lukas.bromig/sila2lib_implementations
